README.md
peer2peer.py
setup.py
peer2peer.egg-info/PKG-INFO
peer2peer.egg-info/SOURCES.txt
peer2peer.egg-info/dependency_links.txt
peer2peer.egg-info/requires.txt
peer2peer.egg-info/top_level.txt