Metadata-Version: 1.0
Name: peer2peer
Version: 2.0.0
Summary: peer 2 peer
Home-page: UNKNOWN
Author: UNKNOWN
Author-email: UNKNOWN
License: MIT
Platform: any
